[
  {
    "title": "Pakistan to protect sanctity of IWT by all means: Tarar",
    "link": "https://www.brecorder.com/news/40427870/pakistan-to-protect-sanctity-of-iwt-by-all-means-tarar",
    "source": "Business Recorder",
    "published": "2026-06-30T13:10:59+05:00"
  },
  {
    "title": "Singapore Households Face Record Power Bills as War Impact Hits",
    "link": "https://www.bloomberg.com/news/articles/2026-06-30/singapore-households-face-record-power-bills-as-war-impact-hits",
    "source": "Bloomberg",
    "published": "2026-06-30T12:22:57+05:00"
  },
  {
    "title": "China Seen Lifting Some Fuel Export Curbs on Ample Supplies",
    "link": "https://www.bloomberg.com/news/articles/2026-06-30/china-seen-lifting-some-fuel-export-curbs-on-ample-supplies",
    "source": "Bloomberg",
    "published": "2026-06-30T12:10:08+05:00"
  },
  {
    "title": "Indian Stocks Beat Emerging Peers, Rupee Rebounds as Oil Slides",
    "link": "https://www.bloomberg.com/news/articles/2026-06-30/indian-stocks-beat-emerging-peers-rupee-rebounds-as-oil-slides",
    "source": "Bloomberg",
    "published": "2026-06-30T12:01:21+05:00"
  },
  {
    "title": "Shell Sees LNG Trade Flat in 2026 as Hormuz Chokes Supply",
    "link": "https://www.bloomberg.com/news/articles/2026-06-30/shell-sees-lng-trade-flat-in-2026-as-hormuz-chokes-supply",
    "source": "Bloomberg",
    "published": "2026-06-30T12:00:00+05:00"
  },
  {
    "title": "India Plans to Add Strategic Fuel Reserves After Iran War Shock",
    "link": "https://www.bloomberg.com/news/articles/2026-06-30/india-plans-to-add-strategic-fuel-reserves-after-iran-war-shock",
    "source": "Bloomberg",
    "published": "2026-06-30T11:43:16+05:00"
  },
  {
    "title": "World Bank Approves $750 Million Kenya Loan, Agrees to Back Loan",
    "link": "https://www.bloomberg.com/news/articles/2026-06-30/world-bank-approves-750-million-kenya-loan-agrees-to-back-loan",
    "source": "Bloomberg",
    "published": "2026-06-30T11:34:59+05:00"
  },
  {
    "title": "Positive sentiments drive PSX, KSE-100 up 1,400 points",
    "link": "https://www.brecorder.com/news/40427850/positive-sentiments-drive-psx-kse-100-up-1400-points",
    "source": "Business Recorder",
    "published": "2026-06-30T11:28:58+05:00"
  },
  {
    "title": "Thailand Looks to Invest in US LNG Projects to Secure Supply",
    "link": "https://www.bloomberg.com/news/articles/2026-06-30/thailand-looks-to-invest-in-us-lng-projects-to-secure-supply",
    "source": "Bloomberg",
    "published": "2026-06-30T11:17:05+05:00"
  },
  {
    "title": "India bond bulls eye breach of key level on US-Iran hopes, index inclusion bets",
    "link": "https://www.brecorder.com/news/40427862/india-bond-bulls-eye-breach-of-key-level-on-us-iran-hopes-index-inclusion-bets",
    "source": "Business Recorder",
    "published": "2026-06-30T11:11:59+05:00"
  },
  {
    "title": "Adani Ports to sell 49% stake in Indian port to MSC for $1.4 billion",
    "link": "https://www.brecorder.com/news/40427843/adani-ports-to-sell-49-stake-in-indian-port-to-msc-for-14-billion",
    "source": "Business Recorder",
    "published": "2026-06-30T11:01:20+05:00"
  },
  {
    "title": "China yuan firms as exporter dollar sales lend support",
    "link": "https://www.brecorder.com/news/40427860/china-yuan-firms-as-exporter-dollar-sales-lend-support",
    "source": "Business Recorder",
    "published": "2026-06-30T10:59:05+05:00"
  },
  {
    "title": "Australian dollar slips to three-month low, RBA no help",
    "link": "https://www.brecorder.com/news/40427859/australian-dollar-slips-to-three-month-low-rba-no-help",
    "source": "Business Recorder",
    "published": "2026-06-30T10:56:20+05:00"
  },
  {
    "title": "Thai May factory output falls 0.8% y/y, weaker than forecast",
    "link": "https://www.brecorder.com/news/40427857/thai-may-factory-output-falls-08-yy-weaker-than-forecast",
    "source": "Business Recorder",
    "published": "2026-06-30T10:48:52+05:00"
  },
  {
    "title": "China stocks rise on upbeat factory data, AI-related export demand",
    "link": "https://www.brecorder.com/news/40427856/china-stocks-rise-on-upbeat-factory-data-ai-related-export-demand",
    "source": "Business Recorder",
    "published": "2026-06-30T10:40:44+05:00"
  },
  {
    "title": "IMF concludes visit to Sri Lanka",
    "link": "https://www.brecorder.com/news/40427855/imf-concludes-visit-to-sri-lanka",
    "source": "Business Recorder",
    "published": "2026-06-30T10:36:24+05:00"
  },
  {
    "title": "OGDCL announces successful completion of Chak well",
    "link": "https://www.brecorder.com/news/40427852/ogdcl-announces-successful-completion-of-chak-well",
    "source": "Business Recorder",
    "published": "2026-06-30T10:33:46+05:00"
  },
  {
    "title": "Pakistan auto industry experts raise concerns over budget measures",
    "link": "https://www.brecorder.com/news/40427726/pakistan-auto-industry-experts-raise-concerns-over-budget-measures",
    "source": "Business Recorder",
    "published": "2026-06-30T10:07:41+05:00"
  },
  {
    "title": "Ex-finance minister Miftah Ismail questions utility of NFC in absence of provincial finance body",
    "link": "https://www.dawn.com/news/2011727/ex-finance-minister-miftah-ismail-questions-utility-of-nfc-in-absence-of-provincial-finance-body",
    "source": "Dawn",
    "published": "2026-06-30T10:02:19+05:00"
  },
  {
    "title": "Oil marketing firm executives booked for ‘multi-billion rupee customs fraud’ in Karachi",
    "link": "https://www.dawn.com/news/2011728/oil-marketing-firm-executives-booked-for-multi-billion-rupee-customs-fraud-in-karachi",
    "source": "Dawn",
    "published": "2026-06-30T08:55:47+05:00"
  },
  {
    "title": "Punjab Assembly okays 38 supplementary budget grants for FY2025-26",
    "link": "https://www.dawn.com/news/2011821/punjab-assembly-okays-38-supplementary-budget-grants-for-fy2025-26",
    "source": "Dawn",
    "published": "2026-06-30T08:38:30+05:00"
  },
  {
    "title": "Fund created to mitigate oil price shocks",
    "link": "https://www.dawn.com/news/2011806/fund-created-to-mitigate-oil-price-shocks",
    "source": "Dawn",
    "published": "2026-06-30T07:59:30+05:00"
  },
  {
    "title": "PM Shehbaz directs major overhaul of agriculture sector",
    "link": "https://www.dawn.com/news/2011799/pm-shehbaz-directs-major-overhaul-of-agriculture-sector",
    "source": "Dawn",
    "published": "2026-06-30T07:53:48+05:00"
  },
  {
    "title": "Week after budget's passage, exporters urge govt to fulfil key demands; seek refund of Rs327bn",
    "link": "https://www.dawn.com/news/2011817/week-after-budgets-passage-exporters-urge-govt-to-fulfil-key-demands-seek-refund-of-rs327bn",
    "source": "Dawn",
    "published": "2026-06-30T07:48:11+05:00"
  },
  {
    "title": "Oil rises on war fears",
    "link": "https://www.dawn.com/news/2011765/oil-rises-on-war-fears",
    "source": "Dawn",
    "published": "2026-06-30T07:34:44+05:00"
  },
  {
    "title": "Flour prices surge in Karachi despite bumper crop, cheap diesel",
    "link": "https://www.dawn.com/news/2011766/flour-prices-surge-in-karachi-despite-bumper-crop-cheap-diesel",
    "source": "Dawn",
    "published": "2026-06-30T07:26:07+05:00"
  },
  {
    "title": "AJK Assembly passes Rs286bn budget for FY27",
    "link": "https://www.dawn.com/news/2011813/ajk-assembly-passes-rs286bn-budget-for-fy27",
    "source": "Dawn",
    "published": "2026-06-30T07:24:13+05:00"
  },
  {
    "title": "Gulf turmoil hurting Pakistan’s economic outlook, say analysts",
    "link": "https://www.dawn.com/news/2011811/gulf-turmoil-hurting-pakistans-economic-outlook-say-analysts",
    "source": "Dawn",
    "published": "2026-06-30T07:20:02+05:00"
  },
  {
    "title": "Oil falls as investors focus on potential Iran-US talks in Doha",
    "link": "https://tribune.com.pk/story/2615716/oil-falls-as-investors-focus-on-potential-iran-us-talks-in-doha",
    "source": "Express Tribune",
    "published": "2026-06-30T06:02:32+05:00"
  },
  {
    "title": "Morgan Stanley Warns of Oil Glut and Cuts Forecasts on Hormuz",
    "link": "https://www.bloomberg.com/news/articles/2026-06-30/morgan-stanley-cuts-oil-forecasts-on-fast-return-of-hormuz-flows",
    "source": "Bloomberg",
    "published": "2026-06-30T05:10:28+05:00"
  }
]